{
  "app": {
    "roots": {
      "title": "Angular fr"
    }
  },
  "auth": {
    "login": {
      "title": "Angular fr",
      "username": {
        "label": "Username fr",
        "error": {
          "required": "This field is required fr."
        }
      },
      "password": {
        "label": "Password fr",
        "error": {
          "required": "This field is required fr."
        }
      },
      "submit": "Submit fr"
    }
  },
  "dashboard": {
    "dashboard": {
      "title": "Dashboard fr",
      "logout": "Logout fr"
    }
  }
}
